{
  "name": "Properties of Metals",
  "icon": "minecraft:iron_ingot",
  "category": "factoryautomation:references",
  "sortnum": 0,
  "pages": [
    {
      "type": "text",
      "text": "A list of the properties of metals, sorted by property.$(br)$(li)$(l:references/0metals#meltingpoints)Melting Points$(li)$(l:references/0metals#densities)Densities$(li)$(l:references/0metals#mhcs)Mass Heat Capacities"
    },
    {
      "type": "empty"
    },
    {
      "type": "factoryautomation:dictionary",
      "title": "Melting Points",
      "anchor": "meltingpoints",
      "i1": "minecraft:iron_ingot",
      "t1": "1,538 \u00B0C",
      "i2": "minecraft:gold_ingot",
      "t2": "10,000 \u00B0C",
      "i3": "minecraft:copper_ingot",
      "t3": "1,084 \u00B0C",
      "i4": "factoryautomation:ingot_tin",
      "t4": "232 \u00B0C",
      "i5": "factoryautomation:ingot_bronze",
      "t5": "950 \u00B0C",
      "i6": "factoryautomation:ingot_steel",
      "t6": "10,000 \u00B0C",
      "i7": "factoryautomation:ingot_pig_iron",
      "t7": "10,000 \u00B0C",
      "i8": "factoryautomation:ingot_magmatic_brass",
      "t8": "10,000 \u00B0C"
    },
    {
      "type": "factoryautomation:dictionary",
      "title": "cont.",
      "i1": "factoryautomation:ingot_silver",
      "t1": "10,000 \u00B0C",
      "i2": "factoryautomation:ingot_lead",
      "t2": "10,000 \u00B0C",
      "i3": "factoryautomation:ingot_nickel",
      "t3": "10,000 \u00B0C",
      "i4": "factoryautomation:ingot_aluminum",
      "t4": "10,000 \u00B0C",
      "i5": "factoryautomation:ingot_aluminum_bronze",
      "t5": "10,000 \u00B0C"
    },
    {
      "type": "factoryautomation:dictionary",
      "title": "Densities",
      "anchor": "densities",
      "i1": "minecraft:iron_ingot",
      "t1": "7,870 kg/m\u00B3",
      "i2": "minecraft:gold_ingot",
      "t2": "19,300 kg/m\u00B3",
      "i3": "minecraft:copper_ingot",
      "t3": "8,933 kg/m\u00B3",
      "i4": "factoryautomation:ingot_tin",
      "t4": "7,310 kg/m\u00B3",
      "i5": "factoryautomation:ingot_bronze",
      "t5": "8,780 kg/m\u00B3",
      "i6": "factoryautomation:ingot_steel",
      "t6": "7,854 kg/m\u00B3",
      "i7": "factoryautomation:ingot_pig_iron",
      "t7": "7,850 kg/m\u00B3",
      "i8": "factoryautomation:ingot_magmatic_brass",
      "t8": "0 kg/m\u00B3"
    },
    {
      "type": "factoryautomation:dictionary",
      "title": "cont.",
      "i1": "factoryautomation:ingot_silver",
      "t1": "10,500 kg/m\u00B3",
      "i2": "factoryautomation:ingot_lead",
      "t2": "11,340 kg/m\u00B3",
      "i3": "factoryautomation:ingot_nickel",
      "t3": "0 kg/m\u00B3",
      "i4": "factoryautomation:ingot_aluminum",
      "t4": "0 kg/m\u00B3",
      "i5": "factoryautomation:ingot_aluminum_bronze",
      "t5": "0 kg/m\u00B3"
    },
    {
      "type": "factoryautomation:dictionary",
      "title": "Mass Heat Capacities",
      "anchor": "mhcs",
      "i1": "minecraft:iron_ingot",
      "t1": "447 J/(kg*K)",
      "i2": "minecraft:gold_ingot",
      "t2": "129 J/(kg*K)",
      "i3": "minecraft:copper_ingot",
      "t3": "385 J/(kg*K)",
      "i4": "factoryautomation:ingot_tin",
      "t4": "227 J/(kg*K)",
      "i5": "factoryautomation:ingot_bronze",
      "t5": "355 J/(kg*K)",
      "i6": "factoryautomation:ingot_steel",
      "t6": "434 J/(kg*K)",
      "i7": "factoryautomation:ingot_pig_iron",
      "t7": "415 J/(kg*K)",
      "i8": "factoryautomation:ingot_magmatic_brass",
      "t8": "0 J/(kg*K)"
    },
    {
      "type": "factoryautomation:dictionary",
      "title": "cont.",
      "i1": "factoryautomation:ingot_silver",
      "t1": "235 J/(kg*K)",
      "i2": "factoryautomation:ingot_lead",
      "t2": "129 J/(kg*K)",
      "i3": "factoryautomation:ingot_nickel",
      "t3": "0 J/(kg*K)",
      "i4": "factoryautomation:ingot_aluminum",
      "t4": "0 J/(kg*K)",
      "i5": "factoryautomation:ingot_aluminum_bronze",
      "t5": "0 J/(kg*K)"
    }
  ]
}